dzh/CLI.py
dzh/GUI.py
dzh/UI.py
dzh/__init__.py
dzh/__main__.py
dzh/hasher.py
dzh-2.0.1.dist-info/.gitignore
dzh-2.0.1.dist-info/LICENSE
dzh-2.0.1.dist-info/METADATA
dzh-2.0.1.dist-info/WHEEL
dzh-2.0.1.dist-info/entry_points.txt
dzh-2.0.1.dist-info/top_level.txt
dzh-2.0.1.dist-info/RECORD
